display.v
module Display(
    input wire clock,
    input wire reset,
    input wire ready,
    input entrada,
    output reg [6:0] saida
);
    
    always @(posedge clock or posedge reset) begin
        if (reset) begin
            saida = 7'b0000000;
        end
        else if (ready) begin
            #1;
            case(entrada)
                1'b0: saida = 7'b0111111;
                1'b1: saida = 7'b0000110;
                default: saida = 7'b1111111;
            endcase
        end
    end

endmodule

codificador.v
module Codificador(
    input wire clock,
    input wire reset,
    input wire ready,
    
    input wire A,
    input wire B,
    input wire C,
    input wire D,

    output wire S3,
    output wire S2,
    output wire S1,
    output wire S0
);

reg S3_reg, S2_reg, S1_reg, S0_reg;

always @(posedge clock or posedge reset) begin
    if (reset) begin
        S3_reg <= 0;
        S2_reg <= 0;
        S1_reg <= 0;
        S0_reg <= 0;
    end else if (ready) begin
        S3_reg <= (A & B & C) | (A & !B & !C) | (!A & C & D) | (!A & !B & D) | (!A & B & !C & !D);
        S2_reg <= (B & C & !D) | (A & !B & D) | (!A & B & D) | (!A & C & D) | (!A & !B & !C & !D);
        S1_reg <= (!C & D) | (!B & D) | (!A & B & !C) | (A & !B & C);
        S0_reg <= (A & !B) | (!B & !D) | (!A & !C & !D) | (A & C & !D);
    end
end

assign S3 = S3_reg;
assign S2 = S2_reg;
assign S1 = S1_reg;
assign S0 = S0_reg;

endmodule

testbench.v

module testbench;

reg clock;
reg reset;
reg ready;
reg [3:0] entrada;
wire [3:0] saida;

reg [3:0] contador;

wire[6:0] display3;

wire[6:0] display2;

wire[6:0] display1;

wire[6:0] display0;

Codificador uut (
    .clock(clock),
    .reset(reset),
    .ready(ready),
    .A(entrada[3]),
    .B(entrada[2]),
    .C(entrada[1]),
    .D(entrada[0]),
    .S3(saida[3]),
    .S2(saida[2]),
    .S1(saida[1]),
    .S0(saida[0])
);

Display display3_uut (.entrada(saida[3]), .saida(display3));
Display display2_uut (.entrada(saida[2]), .saida(display2));
Display display1_uut (.entrada(saida[1]), .saida(display1));
Display display0_uut (.entrada(saida[0]), .saida(display0));


always begin
    #5 clock = !clock;
end

initial begin
    $dumpfile("testbench.vcd");
    $dumpvars(0, testbench);
    $display("A B C D | S3 S2 S1 S0 |> Number3 Number2 Number1 Number0");
    $display("---------------------------");
    
    clock = 0;
    reset = 1;
    ready = 0;
    contador = 4'b0000;

    repeat (16) begin
        entrada = contador;
        reset = 0;
        ready = 1;
        #10;
        ready = 0;
        #10;

       $display("%b %b %b %b | %b  %b  %b  %b  |> %b %b %b %b", entrada[3], entrada[2], entrada[1], entrada[0], saida[3], saida[2], saida[1], saida[0], display3, display2, display1, display0);

        contador = contador + 1;
    end

    $finish;
end

endmodule

testbench.vcd
$date
	Fri Oct  6 21:59:23 2023
$end
$version
	Icarus Verilog
$end
$timescale
	1s
$end
$scope module testbench $end
$var wire 4 ! saida [3:0] $end
$var wire 7 " display3 [6:0] $end
$var wire 7 # display2 [6:0] $end
$var wire 7 $ display1 [6:0] $end
$var wire 7 % display0 [6:0] $end
$var reg 1 & clock $end
$var reg 4 ' contador [3:0] $end
$var reg 4 ( entrada [3:0] $end
$var reg 1 ) ready $end
$var reg 1 * reset $end
$scope module display0_uut $end
$var wire 1 + entrada $end
$var reg 7 , saida [6:0] $end
$upscope $end
$scope module display1_uut $end
$var wire 1 - entrada $end
$var reg 7 . saida [6:0] $end
$upscope $end
$scope module display2_uut $end
$var wire 1 / entrada $end
$var reg 7 0 saida [6:0] $end
$upscope $end
$scope module display3_uut $end
$var wire 1 1 entrada $end
$var reg 7 2 saida [6:0] $end
$upscope $end
$scope module uut $end
$var wire 1 3 A $end
$var wire 1 4 B $end
$var wire 1 5 C $end
$var wire 1 6 D $end
$var wire 1 & clock $end
$var wire 1 ) ready $end
$var wire 1 * reset $end
$var wire 1 7 S3 $end
$var wire 1 8 S2 $end
$var wire 1 9 S1 $end
$var wire 1 : S0 $end
$var reg 1 : S0_reg $end
$var reg 1 9 S1_reg $end
$var reg 1 8 S2_reg $end
$var reg 1 7 S3_reg $end
$upscope $end
$upscope $end
$enddefinitions $end
#0
$dumpvars
x:
x9
x8
x7
06
05
04
03
bx 2
x1
bx 0
x/
bx .
x-
bx ,
x+
0*
1)
b0 (
b0 '
0&
bx %
bx $
bx #
bx "
bx !
$end
#5
b110 %
b110 ,
b111111 $
b111111 .
b110 #
b110 0
b111111 "
b111111 2
1+
0-
1/
01
1:
09
18
b101 !
07
1&
#10
0&
0)
#15
1&
#20
16
0&
1)
b1 (
b1 '
#25
b111111 %
b111111 ,
b110 $
b110 .
b111111 #
b111111 0
b110 "
b110 2
0+
1-
0/
11
0:
19
08
b1010 !
17
1&
#30
0&
0)
#35
1&
#40
15
06
0&
1)
b10 (
b10 '
#45
b110 %
b110 ,
b111111 $
b111111 .
b111111 "
b111111 2
1+
0-
01
1:
09
b1 !
07
1&
#50
0&
0)
#55
1&
#60
16
0&
1)
b11 (
b11 '
#65
b111111 %
b111111 ,
b110 $
b110 .
b110 #
b110 0
b110 "
b110 2
0+
1-
1/
11
0:
19
18
b1110 !
17
1&
#70
0&
0)
#75
1&
#80
14
05
06
0&
1)
b100 (
b100 '
#85
b110 %
b110 ,
b111111 #
b111111 0
1+
0/
1:
b1011 !
08
1&
#90
0&
0)
#95
1&
#100
16
0&
1)
b101 (
b101 '
#105
b111111 %
b111111 ,
b110 #
b110 0
b111111 "
b111111 2
0+
1/
01
0:
18
b110 !
07
1&
#110
0&
0)
#115
1&
#120
15
06
0&
1)
b110 (
b110 '
#125
b111111 $
b111111 .
0-
b100 !
09
1&
#130
0&
0)
#135
1&
#140
16
0&
1)
b111 (
b111 '
#145
b110 "
b110 2
11
b1100 !
17
1&
#150
0&
0)
#155
1&
#160
13
04
05
06
0&
1)
b1000 (
b1000 '
#165
b110 %
b110 ,
b111111 #
b111111 0
1+
0/
1:
b1001 !
08
1&
#170
0&
0)
#175
1&
#180
16
0&
1)
b1001 (
b1001 '
#185
b110 $
b110 .
b110 #
b110 0
1-
1/
19
b1111 !
18
1&
#190
0&
0)
#195
1&
#200
15
06
0&
1)
b1010 (
b1010 '
#205
b111111 #
b111111 0
b111111 "
b111111 2
0/
01
08
b11 !
07
1&
#210
0&
0)
#215
1&
#220
16
0&
1)
b1011 (
b1011 '
#225
b110 #
b110 0
1/
b111 !
18
1&
#230
0&
0)
#235
1&
#240
14
05
06
0&
1)
b1100 (
b1100 '
#245
b111111 %
b111111 ,
b111111 $
b111111 .
b111111 #
b111111 0
0+
0-
0/
0:
09
b0 !
08
1&
#250
0&
0)
#255
1&
#260
16
0&
1)
b1101 (
b1101 '
#265
b110 $
b110 .
1-
b10 !
19
1&
#270
0&
0)
#275
1&
#280
15
06
0&
1)
b1110 (
b1110 '
#285
b110 %
b110 ,
b111111 $
b111111 .
b110 #
b110 0
b110 "
b110 2
1+
0-
1/
11
1:
09
18
b1101 !
17
1&
#290
0&
0)
#295
1&
#300
16
0&
1)
b1111 (
b1111 '
#305
b111111 %
b111111 ,
b111111 #
b111111 0
0+
0/
0:
b1000 !
08
1&
#310
0&
0)
#315
1&
#320
0&
b0 '
